vxwassup/__init__.py
vxwassup/throttle.py
vxwassup/transport.py
vxwassup-1.2.1.dist-info/DESCRIPTION.rst
vxwassup-1.2.1.dist-info/METADATA
vxwassup-1.2.1.dist-info/RECORD
vxwassup-1.2.1.dist-info/WHEEL
vxwassup-1.2.1.dist-info/metadata.json
vxwassup-1.2.1.dist-info/top_level.txt
