Metadata-Version: 2.0
Name: vxwassup
Version: 1.2.1
Summary: vxwassup
Home-page: https://github.com/praekeltfoundation/wa-transport
Author: Simon de Haan
Author-email: simon@praekelt.org
License: UNKNOWN
Keywords: vxwassup vumi
Platform: UNKNOWN
Classifier: Intended Audience :: Developers
Classifier: Natural Language :: English
Classifier: Programming Language :: Python :: 2.7
Requires-Dist: junebug (>=0.1.23)
Provides-Extra: dev
Requires-Dist: pytest; extra == 'dev'
Requires-Dist: pytest-cov; extra == 'dev'
Requires-Dist: pytest-xdist; extra == 'dev'
Requires-Dist: mock; extra == 'dev'
Requires-Dist: twine; extra == 'dev'
Requires-Dist: flake8; extra == 'dev'
